Metadata-Version: 1.1
Name: gigatronapi
Version: 0.0.2
Summary: Gigatron API Wrapper
Home-page: UNKNOWN
Author: Darko Dekan
Author-email: darko.dekan@protonmail.com
License: The Unlicense (Unlicense)
Keywords: gigatron
Platform: UNKNOWN
Classifier: Development Status :: 5 - Production/Stable
Classifier: Intended Audience :: Developers
Classifier: Operating System :: POSIX :: Linux
Classifier: License :: OSI Approved :: The Unlicense (Unlicense)
Classifier: Programming Language :: Python :: 3.9
